stock_picking/__init__.py
stock_picking/fetch_data.py
stock_picking/piotroski_score.py
stock_picking/top_stocks.py
stock_picking-0.1.1.dist-info/LICENSE
stock_picking-0.1.1.dist-info/METADATA
stock_picking-0.1.1.dist-info/WHEEL
stock_picking-0.1.1.dist-info/top_level.txt
stock_picking-0.1.1.dist-info/RECORD
